imandra/__init__.py
imandra/auth.py
imandra/ipl.py
imandra/session.py
imandra/__pycache__/__init__.cpython-313.pyc
imandra/__pycache__/auth.cpython-313.pyc
imandra/__pycache__/core.cpython-313.pyc
imandra/api/__init__.py
imandra/api/auth.py
imandra/api/cfb.py
imandra/api/instance.py
imandra/api/ipl.py
imandra/api/ipl_common.py
imandra/api/rule_synth.py
imandra/cli/__init__.py
imandra/cli/ipl_log_analysis.py
imandra/core/__init__.py
imandra/u/__init__.py
imandra/u/agents/__init__.py
imandra/u/agents/__pycache__/__init__.cpython-313.pyc
imandra/u/agents/__pycache__/code_logician.cpython-313.pyc
imandra/u/agents/__pycache__/code_logician_formalizer.cpython-313.pyc
imandra/u/agents/__pycache__/code_logician_reasoner.cpython-313.pyc
imandra/u/agents/__pycache__/cogito.cpython-313.pyc
imandra/u/agents/code_logician/__init__.py
imandra/u/agents/code_logician/command.py
imandra/u/agents/code_logician/interrupt_message.py
imandra/u/agents/code_logician/rich_utils.py
imandra/u/agents/code_logician/runtime_context.py
imandra/u/agents/code_logician/task.py
imandra/u/agents/code_logician/__pycache__/__init__.cpython-312.pyc
imandra/u/agents/code_logician/__pycache__/__init__.cpython-313.pyc
imandra/u/agents/code_logician/__pycache__/command.cpython-312.pyc
imandra/u/agents/code_logician/__pycache__/command.cpython-313.pyc
imandra/u/agents/code_logician/__pycache__/command_schema.cpython-312.pyc
imandra/u/agents/code_logician/__pycache__/graph.cpython-312.pyc
imandra/u/agents/code_logician/__pycache__/graph.cpython-313.pyc
imandra/u/agents/code_logician/__pycache__/graph_state_schema.cpython-312.pyc
imandra/u/agents/code_logician/base/__init__.py
imandra/u/agents/code_logician/base/context.py
imandra/u/agents/code_logician/base/dependency.py
imandra/u/agents/code_logician/base/formalization_state.py
imandra/u/agents/code_logician/base/imandrax.py
imandra/u/agents/code_logician/base/iml.py
imandra/u/agents/code_logician/base/region_decomp.py
imandra-2.4.1.dist-info/METADATA
imandra-2.4.1.dist-info/WHEEL
imandra-2.4.1.dist-info/entry_points.txt
imandra-2.4.1.dist-info/top_level.txt
imandra-2.4.1.dist-info/RECORD
