Metadata-Version: 2.4
Name: imandra
Version: 2.4.1
Summary: A CLI and API client library for interfacing with Imandra's web APIs
Keywords: imandra
Requires-Python: >=3.12
Requires-Dist: requests>=2
Requires-Dist: platformdirs>=4.3
Provides-Extra: core
Requires-Dist: imandrax-api[async]>=0.18.0.1; extra == "core"
Provides-Extra: http-api-client
Requires-Dist: aenum>=3.1.11; extra == "http-api-client"
Requires-Dist: python_dateutil>=2.5.3; extra == "http-api-client"
Requires-Dist: pydantic<2,>=1.10.5; extra == "http-api-client"
Requires-Dist: urllib3<2.1.0,>=1.25.3; extra == "http-api-client"
Provides-Extra: universe
Requires-Dist: devtools>=0.12.2; extra == "universe"
Requires-Dist: imandrax-api-models>=18; extra == "universe"
Requires-Dist: imandrax-api[async]>=0.18.0.1; extra == "universe"
Requires-Dist: langgraph>=0.2.63; extra == "universe"
Requires-Dist: langgraph-sdk<0.3; extra == "universe"
Requires-Dist: rich>=14.0.0; extra == "universe"
Provides-Extra: async
Requires-Dist: aiohttp; extra == "async"
Provides-Extra: dev
Requires-Dist: ipykernel>=6.29.5; extra == "dev"
Requires-Dist: pytest>=8.4.2; extra == "dev"
Requires-Dist: pytest-asyncio>=1.2.0; extra == "dev"
